__init__.py
cool_gpt/__init__.py
cool_gpt/bot.py
cool_gpt/speech_to_text/__init__.py
cool_gpt/speech_to_text/speech_to_text.py
cool_gpt/speech_to_text/speech_to_text_whisper.py
cool_gpt/text_to_speech/__init__.py
cool_gpt/text_to_speech/text_to_speech.py
cool_gpt-0.0.2.dist-info/LICENSE
cool_gpt-0.0.2.dist-info/METADATA
cool_gpt-0.0.2.dist-info/WHEEL
cool_gpt-0.0.2.dist-info/top_level.txt
cool_gpt-0.0.2.dist-info/RECORD
