Metadata-Version: 2.1
Name: cool-gpt
Version: 0.0.2
Summary: A Python package that can help you to generate text using ChatGPT via scraping.
Author-email: dipeshpal <dipeshpal17@gmail.com>
Project-URL: Homepage, https://github.com/Dipeshpal/cool-gpt
Project-URL: Bug Tracker, https://github.com/Dipeshpal/cool-gpt/issues
Classifier: Programming Language :: Python :: 3
Classifier: License :: OSI Approved :: MIT License
Classifier: Operating System :: OS Independent
Requires-Python: >=3.7
License-File: LICENSE
